{"char": {"id": "CHAR_618", "name": "Ananias of Damascus", "icon": "", "type": "character", "tier": "Supporting", "canon": "Canonical", "era": "Early Church", "faction": "The Early Church", "personality": "Obedient", "city": "Damascus", "hometown": "", "available_from_day": null, "died_day": null, "bio": "A disciple in Damascus. The Lord told me in a vision to go lay hands on Saul, the very man who'd come to arrest us! I argued. But I went, said 'Brother Saul,' and scales fell from his eyes. Sometimes obedience means walking straight toward your fear.", "work": "Disciple", "badge": ""}, "friends": [], "friends_count": 0, "followers": 12, "posts": []}