{"char": {"id": "CHAR_769", "name": "Maalon", "icon": "", "type": "character", "tier": "NPC", "canon": "Fictional", "era": "Monarchy", "faction": "House of Levi", "personality": "Faithful", "city": "Jerusalem", "hometown": "", "available_from_day": null, "died_day": null, "bio": "A Levite, a gatekeeper for the tent that holds the ark of God. I keep the thresholds, guard the holy things, open and close at the appointed times. When the temple's finished they say there'll be thousands of us in courses. For now, I keep my post.", "work": "Levite Gatekeeper", "badge": ""}, "friends": [], "friends_count": 0, "followers": 0, "posts": []}