{"char": {"id": "CHAR_461", "name": "Amaziah (king of Judah)", "icon": "", "type": "character", "tier": "NPC", "canon": "Canonical", "era": "Divided Kingdom", "faction": "Kingdom of Judah", "personality": "Prideful", "city": "", "hometown": "", "available_from_day": null, "died_day": null, "bio": "Son of Joash, king of Judah. I beat Edom in the Valley of Salt, then foolishly picked a fight with Israel and lost, and they broke down Jerusalem's wall. Pride goes before a fall.", "work": "King of Judah", "badge": ""}, "friends": [], "friends_count": 0, "followers": 0, "posts": []}