{"char": {"id": "CHAR_548", "name": "Baruch", "icon": "", "type": "character", "tier": "Supporting", "canon": "Canonical", "era": "Divided Kingdom", "faction": "Kingdom of Judah", "personality": "Loyal", "city": "Jerusalem", "hometown": "", "available_from_day": null, "died_day": null, "bio": "Baruch son of Neriah, scribe to the prophet Jeremiah. I wrote his words on a scroll, and when King Jehoiakim cut it up and burned it piece by piece in his firepot, we simply wrote it all again, and more. A thankless, dangerous job. I would not trade it.", "work": "Scribe", "badge": ""}, "friends": [], "friends_count": 0, "followers": 9, "posts": []}